{
    "co.aikar.util": "us.minevict.mvutil.dependencies.co.aikar.util",
    "co.aikar.commands": "us.minevict.mvutil.dependencies.co.aikar.commands",
    "co.aikar.locales": "us.minevict.mvutil.dependencies.co.aikar.locales",
    "co.aikar.idb": "us.minevict.mvutil.dependencies.co.aikar.idb",
    "org.apache.commons.lang": "us.minevict.mvutil.dependencies.org.apache.commons.lang",
    "com.zaxxer": "us.minevict.mvutil.dependencies.com.zaxxer",
    "org.slf4j": "us.minevict.mvutil.dependencies.org.slf4j",
    "net.jodah.expiringmap": "us.minevict.mvutil.dependencies.net.jodah.expiringmap",
    "org.jetbrains.annotations": "us.minevict.mvutil.dependencies.org.jetbrains.annotations",
    "org.intellij.lang.annotations": "us.minevict.mvutil.dependencies.org.intellij.lang.annotations",
    "kotlin": "us.minevict.mvutil.dependencies.kotlin",
    "org.jetbrains.kotlin": "us.minevict.mvutil.dependencies.org.jetbrains.kotlin",
    "com.google.gson": "us.minevict.mvutil.dependencies.com.google.gson",
    "org.apache.commons.pool2": "us.minevict.mvutil.dependencies.org.apache.commons.pool2",
    "redis.clients.jedis": "us.minevict.mvutil.dependencies.redis.clients.jedis",
    "com.moandjiezana.toml": "us.minevict.mvutil.dependencies.com.moandjiezana.toml",
    "de.themoep.minedown": "us.minevict.mvutil.dependencies.de.themoep.minedown"
}
